ruapu.abi3.so
ruapu-0.1.0.dist-info/RECORD
ruapu-0.1.0.dist-info/LICENSE
ruapu-0.1.0.dist-info/WHEEL
ruapu-0.1.0.dist-info/top_level.txt
ruapu-0.1.0.dist-info/METADATA
