Metadata-Version: 2.1
Name: ruapu
Version: 0.1.0
Summary: The Python binding of ruapu.
Author-email: nihui <shuizhuyuanluo@126.com>, cocoa-xu <i@uwucocoa.moe>
License: MIT
Project-URL: Homepage, https://github.com/nihui/ruapu
Keywords: ruapu,cpu,isa,detect
Requires-Python: >=3.5
License-File: LICENSE
